{
	"info": {
		"_postman_id": "461f14a5-f0b0-4f3a-821e-f38714ad13e0",
		"name": "Pract-1_",
		"schema": "https://schema.getpostman.com/json/collection/v2.1.0/collection.json",
		"_exporter_id": "33194097"
	},
	"item": [
		{
			"name": "Create user",
			"request": {
				"method": "POST",
				"header": [],
				"body": {
					"mode": "raw",
					"raw": "{\r\n    \"firstName\": \"firstName-1\",\r\n    \"lastName\": \"lastName-1\",\r\n    \"login\":\"login-1\",\r\n    \"password\": \"password-1\"\r\n}",
					"options": {
						"raw": {
							"language": "json"
						}
					}
				},
				"url": {
					"raw": "http://localhost:8080/users",
					"protocol": "http",
					"host": [
						"localhost"
					],
					"port": "8080",
					"path": [
						"users"
					]
				}
			},
			"response": []
		},
		{
			"name": "Get all users",
			"request": {
				"method": "GET",
				"header": [],
				"url": {
					"raw": "http://localhost:8080/users",
					"protocol": "http",
					"host": [
						"localhost"
					],
					"port": "8080",
					"path": [
						"users"
					]
				}
			},
			"response": []
		},
		{
			"name": "Login",
			"request": {
				"method": "POST",
				"header": [],
				"body": {
					"mode": "raw",
					"raw": "{\r\n    \"login\": \"login-1\",\r\n    \"password\": \"password-1\"\r\n}",
					"options": {
						"raw": {
							"language": "json"
						}
					}
				},
				"url": {
					"raw": "http://localhost:8080/login",
					"protocol": "http",
					"host": [
						"localhost"
					],
					"port": "8080",
					"path": [
						"login"
					]
				}
			},
			"response": []
		},
		{
			"name": "Create order",
			"request": {
				"method": "POST",
				"header": [
					{
						"key": "Authorization",
						"value": "cbe1fed7-c93c-4dac-a7b2-536b2924f3c0",
						"type": "text"
					}
				],
				"body": {
					"mode": "raw",
					"raw": "{\r\n    \"from\": \"address - 1\",\r\n    \"to\": \"address - 2\"\r\n}",
					"options": {
						"raw": {
							"language": "json"
						}
					}
				},
				"url": {
					"raw": "http://localhost:8080/orders",
					"protocol": "http",
					"host": [
						"localhost"
					],
					"port": "8080",
					"path": [
						"orders"
					]
				}
			},
			"response": []
		},
		{
			"name": "Get orders by user",
			"request": {
				"method": "GET",
				"header": [
					{
						"key": "Authorization",
						"value": "a89e42d8-972a-4590-aa40-be8e873d3713",
						"type": "text"
					}
				],
				"url": {
					"raw": "http://localhost:8080/orders",
					"protocol": "http",
					"host": [
						"localhost"
					],
					"port": "8080",
					"path": [
						"orders"
					]
				}
			},
			"response": []
		},
		{
			"name": "Get last 5 from point",
			"request": {
				"method": "GET",
				"header": [],
				"url": {
					"raw": "http://localhost:8080/orders/from",
					"protocol": "http",
					"host": [
						"localhost"
					],
					"port": "8080",
					"path": [
						"orders",
						"from"
					]
				}
			},
			"response": []
		},
		{
			"name": "Last 3 to",
			"request": {
				"method": "GET",
				"header": []
			},
			"response": []
		},
		{
			"name": "Get lowest Price",
			"request": {
				"method": "GET",
				"header": []
			},
			"response": []
		},
		{
			"name": "New Request",
			"request": {
				"method": "GET",
				"header": []
			},
			"response": []
		}
	]
}